classfactory/__init__.py
classfactory/classfactory.py
Simple_Class_Factory-0.0.1.dist-info/METADATA
Simple_Class_Factory-0.0.1.dist-info/WHEEL
Simple_Class_Factory-0.0.1.dist-info/top_level.txt
Simple_Class_Factory-0.0.1.dist-info/RECORD
